pybernetics/DataTypes.py
pybernetics/Datasets.py
pybernetics/Layers.py
pybernetics/Loss.py
pybernetics/Models.py
pybernetics/NaturalLanguageProcessing.py
pybernetics/Optimizers.py
pybernetics/PyArrays.py
pybernetics/Training.py
pybernetics/_Typing.py
pybernetics/_Utils.py
pybernetics/__init__.py
pybernetics-0.1.1.dist-info/LICENSE.txt
pybernetics-0.1.1.dist-info/METADATA
pybernetics-0.1.1.dist-info/WHEEL
pybernetics-0.1.1.dist-info/top_level.txt
pybernetics-0.1.1.dist-info/RECORD
